./.gitignore
./PKG-INFO
./README.md
./py.typed
./pyproject.toml
./example/README.md
./example/__init__.py
./example/env.example
./example/pyproject.toml
./example/qwen_realtime_example.py
./tests/test_qwen_realtime.py
./vision_agents/plugins/qwen/__init__.py
./vision_agents/plugins/qwen/client.py
./vision_agents/plugins/qwen/events.py
./vision_agents/plugins/qwen/qwen_realtime.py
vision_agents_plugins_qwen-0.2.10.dist-info/METADATA
vision_agents_plugins_qwen-0.2.10.dist-info/WHEEL
vision_agents_plugins_qwen-0.2.10.dist-info/RECORD
